pyowapi/__init__.py
pyowapi/tests/__init__.py
pyowapi/tests/test_api.py
pyowapi/tests/test_rank.py
pyowapi-3.0.0.dist-info/LICENSE.md
pyowapi-3.0.0.dist-info/METADATA
pyowapi-3.0.0.dist-info/WHEEL
pyowapi-3.0.0.dist-info/top_level.txt
pyowapi-3.0.0.dist-info/RECORD
