Metadata-Version: 2.1
Name: pyowapi
Version: 3.0.0
Summary: An asynchronous wrapper for ow-api.com using aiohttp
Home-page: https://github.com/zusorio/pyowapi
Author: Tobias Messner
Author-email: tobias@zusor.io
Classifier: Programming Language :: Python :: 3
Classifier: License :: OSI Approved :: MIT License
Classifier: Operating System :: OS Independent
Requires-Python: >=3.8
License-File: LICENSE.md
Requires-Dist: aiohttp
